envars/__init__.py
envars/envars.py
envars/tests/__init__.py
envars/tests/test_envars.py
envars-0.3.5.dist-info/DESCRIPTION.rst
envars-0.3.5.dist-info/METADATA
envars-0.3.5.dist-info/RECORD
envars-0.3.5.dist-info/WHEEL
envars-0.3.5.dist-info/metadata.json
envars-0.3.5.dist-info/top_level.txt
